MANIFEST.in
setup.cfg
setup.py
packageskel/__init__.py
packageskel/main.py
packageskel/packageskel.py
packageskel/wingdbstub.py
packageskel.egg-info/PKG-INFO
packageskel.egg-info/SOURCES.txt
packageskel.egg-info/dependency_links.txt
packageskel.egg-info/entry_points.txt
packageskel.egg-info/top_level.txt
packageskel/templates/default/LICENSE.txt
packageskel/templates/default/Makefile
packageskel/templates/default/README.md
packageskel/templates/default/configuration.mk
packageskel/templates/default/requirements.txt
packageskel/templates/default/setup.cfg
packageskel/templates/default/setup.py
packageskel/templates/default/make-includes/.gitignore
packageskel/templates/default/make-includes/.travis.yml
packageskel/templates/default/make-includes/LICENSE.txt
packageskel/templates/default/make-includes/Makefile
packageskel/templates/default/make-includes/README.md
packageskel/templates/default/make-includes/posix-shell.mk
packageskel/templates/default/make-includes/post-build.mk
packageskel/templates/default/make-includes/python.mk
packageskel/templates/default/make-includes/sort.xslt
packageskel/templates/default/make-includes/variables.mk
packageskel/templates/default/make-includes/xml.mk
packageskel/templates/default/packageskel/__init__.py
packageskel/templates/default/packageskel/packageskel.py
packageskel/templates/default/tests/__init__.py
packageskel/templates/default/tests/packageskel_tests.py
packageskel/templates/default/tests/utilities.py