Metadata-Version: 1.1
Name: packageskel
Version: 0.0.1
Summary: A python package skeleton/template creator.
Home-page: https://github.com/jnvilo/packageskel
Author: Jason Viloria
Author-email: jnvilo@gmail.com
License: UNKNOWN
Download-URL: https://github.com/jnvilo/packageskel/archive/master.zip
Keywords: packaging,package,skeleton,template
Platform: UNKNOWN
Classifier: Development Status :: 3 - Alpha
Classifier: Environment :: Console
Classifier: Intended Audience :: Developers
Classifier: License :: OSI Approved :: GNU General Public License v3 or later (GPLv3+)
Classifier: Operating System :: POSIX
Classifier: Programming Language :: Python
Classifier: Programming Language :: Python :: 2.6
Classifier: Programming Language :: Python :: 2.7
Classifier: Programming Language :: Python :: 3.3
Classifier: Programming Language :: Python :: 3.4
Classifier: Programming Language :: Python :: 3.5
Classifier: Programming Language :: Python :: 3.6
Classifier: Programming Language :: Python :: Implementation :: CPython
Classifier: Programming Language :: Python :: Implementation :: PyPy
Classifier: Topic :: Software Development
